{
  "version": "1.0.0",
  "restore": {
    "projectUniqueName": "C:\\Users\\sahin\\source\\repos\\Tweetbook\\Tweetbook\\Tweetbook.csproj",
    "projectName": "Tweetbook",
    "projectPath": "C:\\Users\\sahin\\source\\repos\\Tweetbook\\Tweetbook\\Tweetbook.csproj",
    "outputPath": "C:\\Users\\sahin\\source\\repos\\Tweetbook\\Tweetbook\\obj\\",
    "projectStyle": "PackageReference",
    "fallbackFolders": [
      "C:\\Program Files\\dotnet\\sdk\\NuGetFallbackFolder"
    ],
    "originalTargetFrameworks": [
      "netcoreapp2.2"
    ],
    "sources": {
      "C:\\Program Files (x86)\\Microsoft SDKs\\NuGetPackages\\": {},
      "https://api.nuget.org/v3/index.json": {}
    },
    "frameworks": {
      "netcoreapp2.2": {
        "projectReferences": {}
      }
    },
    "warningProperties": {
      "warnAsError": [
        "NU1605"
      ]
    }
  },
  "frameworks": {
    "netcoreapp2.2": {
      "dependencies": {
        "Microsoft.AspNetCore.App": {
          "suppressParent": "All",
          "target": "Package",
          "version": "[2.2.0, )",
          "autoReferenced": true
        },
        "Microsoft.AspNetCore.Razor.Design": {
          "suppressParent": "All",
          "target": "Package",
          "version": "[2.2.0, )"
        },
        "Microsoft.EntityFrameworkCore": {
          "target": "Package",
          "version": "[2.2.6, )"
        },
        "Microsoft.EntityFrameworkCore.SqlServer": {
          "target": "Package",
          "version": "[2.2.6, )"
        },
        "Microsoft.EntityFrameworkCore.Tools": {
          "include": "Runtime, Build, Native, ContentFiles, Analyzers",
          "suppressParent": "All",
          "target": "Package",
          "version": "[2.2.0, )"
        },
        "Microsoft.EntityFrameworkCore.Tools.DotNet": {
          "target": "Package",
          "version": "[2.0.3, )"
        },
        "Microsoft.NETCore.App": {
          "suppressParent": "All",
          "target": "Package",
          "version": "[2.2.0, )",
          "autoReferenced": true
        },
        "Swashbuckle.AspNetCore": {
          "target": "Package",
          "version": "[4.0.1, )"
        },
        "Swashbuckle.AspNetCore.Swagger": {
          "target": "Package",
          "version": "[4.0.1, )"
        }
      },
      "imports": [
        "net461",
        "net462",
        "net47",
        "net471",
        "net472",
        "net48"
      ],
      "assetTargetFallback": true,
      "warn": true
    }
  }
}